cligo/__init__.py
cligo/cli.py
cligo/command.py
cligo/exceptions.py
cligo/core/__init__.py
cligo/core/error.py
cligo/core/renderer.py
cligo/core/templates.py
cligo/core/management/__init__.py
cligo/core/management/commands.py
cligo/output/__init__.py
cligo/output/colors.py
cligo/output/outputHandler.py
cligo/permissions/__init__.py
cligo/permissions/base.py
cligo/utils/__init__.py
cligo/utils/dataTools.py
cligo/utils/funcTools.py
tests/__init__.py
tests/base.py
tests/test_cli.py
tests/test_cli_core.py
tests/test_exceptions.py
tests/test_permissions.py
tests/utils/__init__.py
tests/utils/commands.py
tests/utils/errors.py
tests/utils/exceptions.py
tests/utils/models.py
tests/utils/permissions.py
Cligo-1.2.1.dist-info/LICENSE.md
Cligo-1.2.1.dist-info/METADATA
Cligo-1.2.1.dist-info/WHEEL
Cligo-1.2.1.dist-info/entry_points.txt
Cligo-1.2.1.dist-info/top_level.txt
Cligo-1.2.1.dist-info/RECORD
