Metadata-Version: 2.1
Name: Cligo
Version: 1.2.1
Summary: A Python CLI Framework.
Home-page: https://github.com/AidenEllis/Cligo
Author: Aiden Ellis
Author-email: itsaidenellis@protonmail.com
License: MIT
Project-URL: Github, https://github.com/AidenEllis/Cligo
Project-URL: Documentation, https://github.com/AidenEllis/Cligo/blob/main/docs
Project-URL: Issue tracker, https://github.com/AidenEllis/Cligo/issues
Keywords: cligo,cli,cli go,python cli framework,CLI Framework,Command Line Interface
Platform: UNKNOWN
Classifier: Development Status :: 5 - Production/Stable
Classifier: Programming Language :: Python :: 3
Classifier: Operating System :: OS Independent
Classifier: License :: OSI Approved :: MIT License
Classifier: Natural Language :: English
Classifier: Intended Audience :: Developers
Classifier: Topic :: Software Development :: Libraries
Classifier: Topic :: Software Development :: Libraries :: Python Modules
Classifier: Topic :: Utilities
License-File: LICENSE.md
Requires-Dist: asgiref (==3.4.1)
Requires-Dist: certifi (==2021.5.30)
Requires-Dist: colorama (==0.4.4)
Requires-Dist: cx-Freeze (==6.7)
Requires-Dist: cx-Logging (==3.0)
Requires-Dist: importlib-metadata (==4.6.1)
Requires-Dist: Jinja2 (==3.0.1)
Requires-Dist: MarkupSafe (==2.0.1)
Requires-Dist: peewee (==3.14.4)
Requires-Dist: pytz (==2021.1)
Requires-Dist: sqlparse (==0.4.1)
Requires-Dist: wincertstore (==0.2)
Requires-Dist: zipp (==3.5.0)
